md_wash/__init__.py
md_wash/__main__.py
md_wash/md_wash.py
md_wash/logx/__init__.py
md_wash/logx/colored_handler.py
md_wash/logx/logging.yaml
md_wash/logx/setup_logging.py
md_wash-0.0.24.dist-info/METADATA
md_wash-0.0.24.dist-info/WHEEL
md_wash-0.0.24.dist-info/entry_points.txt
md_wash-0.0.24.dist-info/top_level.txt
md_wash-0.0.24.dist-info/RECORD
