Metadata-Version: 2.1
Name: md-wash
Version: 0.0.24
Summary: this is a description
Home-page: https://github.com/zk4/md_wash
Author: zk
Author-email: liuzq7@gmail.com
License: BSD
Download-URL: https://github.com/zk4/md_wash/archive/master.zip
Keywords: best practice for python project
Platform: UNKNOWN
Classifier: Development Status :: 5 - Production/Stable
Classifier: Environment :: Console
Requires-Python: >3.0.0
Requires-Dist: requests (==2.26.0)
Requires-Dist: pytest (==5.2.1)
Requires-Dist: PyYAML (==6.0)
